{
    "name": "Global Information",
    "numberOfRequests": {
        "total": 967,
        "ok": 967,
        "ko": 0
    },
    "minResponseTime": {
        "total": 104,
        "ok": 104,
        "ko": 0
    },
    "maxResponseTime": {
        "total": 3317,
        "ok": 3317,
        "ko": 0
    },
    "meanResponseTime": {
        "total": 117,
        "ok": 117,
        "ko": 0
    },
    "standardDeviation": {
        "total": 116,
        "ok": 116,
        "ko": 0
    },
    "percentiles1": {
        "total": 110,
        "ok": 110,
        "ko": 0
    },
    "percentiles2": {
        "total": 112,
        "ok": 112,
        "ko": 0
    },
    "percentiles3": {
        "total": 117,
        "ok": 117,
        "ko": 0
    },
    "percentiles4": {
        "total": 180,
        "ok": 180,
        "ko": 0
    },
    "group1": {
    "name": "t < 800 ms",
    "count": 964,
    "percentage": 100
},
    "group2": {
    "name": "800 ms < t < 1200 ms",
    "count": 1,
    "percentage": 0
},
    "group3": {
    "name": "t > 1200 ms",
    "count": 2,
    "percentage": 0
},
    "group4": {
    "name": "failed",
    "count": 0,
    "percentage": 0
},
    "meanNumberOfRequestsPerSecond": {
        "total": 14.014492753623188,
        "ok": 14.014492753623188,
        "ko": 0
    }
}